cleer/__init__.py
cleer-0.1.0a1.dist-info/LICENSE
cleer-0.1.0a1.dist-info/METADATA
cleer-0.1.0a1.dist-info/WHEEL
cleer-0.1.0a1.dist-info/top_level.txt
cleer-0.1.0a1.dist-info/RECORD
